interrail/__init__.py
interrail/api.py
interrail/data.py
interrail-0.0.3.dist-info/LICENSE
interrail-0.0.3.dist-info/METADATA
interrail-0.0.3.dist-info/WHEEL
interrail-0.0.3.dist-info/top_level.txt
interrail-0.0.3.dist-info/RECORD
