Metadata-Version: 2.1
Name: interrail
Version: 0.0.3
Summary: A wrapper around the Interrail api
Home-page: https://github.com/ThijmenStar/py-interrail
Author: Thijmen Star
License: UNKNOWN
Platform: UNKNOWN
Classifier: Programming Language :: Python :: 3
Classifier: License :: OSI Approved :: MIT License
Classifier: Operating System :: OS Independent
License-File: LICENSE
Requires-Dist: requests
Requires-Dist: importlib ; python_version == "2.6"
